gravlax_calculator/__init__.py
gravlax_calculator/calculator.py
gravlax_calculator-1.1.1.dist-info/licenses/LICENSE
gravlax_calculator-1.1.1.dist-info/METADATA
gravlax_calculator-1.1.1.dist-info/WHEEL
gravlax_calculator-1.1.1.dist-info/entry_points.txt
gravlax_calculator-1.1.1.dist-info/top_level.txt
gravlax_calculator-1.1.1.dist-info/RECORD
