Metadata-Version: 2.4
Name: gravlax_calculator
Version: 1.1.1
Summary: Gravlax calculator, a small tax calculator
Author: Alexandre Gravereaux
License-Expression: MIT
Project-URL: Homepage, https://github.com/alexgravx/perso-gravlax-calculator/
Classifier: Programming Language :: Python :: 3
Classifier: Operating System :: OS Independent
Requires-Python: >=3.11.8
License-File: LICENSE
Dynamic: license-file
